plushcap
