Metadata-Version: 1.1
Name: plushcap
Version: 0.2.2
Summary: Plushcap monitors websites and alerts people via text or phone call if there is a problem.
Home-page: https://github.com/makaimc/plushcap
Author: Matt Makai
Author-email: mmakai@twilio.com
License: BSD
Keywords: plushcap
Platform: UNKNOWN
Classifier: Development Status :: 2 - Pre-Alpha
Classifier: Intended Audience :: Developers
Classifier: License :: OSI Approved :: BSD License
Classifier: Natural Language :: English
Classifier: Programming Language :: Python :: 2
Classifier: Programming Language :: Python :: 2.6
Classifier: Programming Language :: Python :: 2.7
Classifier: Programming Language :: Python :: 3
Classifier: Programming Language :: Python :: 3.3
Classifier: Programming Language :: Python :: 3.4
